{
  "name": "Sys::Lastlog",
  "source-url": "git://github.com/jonathanstowe/p6-Sys-Lastlog.git",
  "support": {
    "irc": "irc://irc.freenode.net/#perl6",
    "source": "git://github.com/jonathanstowe/p6-Sys-Lastlog.git",
    "email": "jns+git@gellyfish.co.uk",
    "bugtracker": "https://github.com/jonathanstowe/p6-Sys-Lastlog/issues"
  },
  "perl": "6",
  "resources": [
    "libraries/lastloghelper"
  ],
  "build-depends": [
    "LibraryMake",
    "Shell::Command"
  ],
  "author": "Jonathan Stowe <jns+git@gellyfish.co.uk>",
  "auth": "github:jonathanstowe",
  "depends": [
    "System::Passwd"
  ],
  "tags": [
    "unix",
    "audit",
    "lastlog"
  ],
  "license": "Artistic-2.0",
  "test-depends": [
    "Test"
  ],
  "provides": {
    "Sys::Lastlog": "lib/Sys/Lastlog.pm"
  },
  "version": "0.0.9",
  "authors": [
    "Jonathan Stowe <jns+git@gellyfish.com>"
  ],
  "description": "Perl 6 access to Lastlog information on Unix-like systems",
  "meta6": "0"
}
