
{
    "perl"         : "6.c",
    "name"         : "Web::Cache",
    "license"      : "Artistic-2.0",
    "version"      : "0.000001",
    "description"  : "Perl 6 web-framework-neutral LRU caching module",
    "tags"         : [ "Web", "Cache", "LRU" ],
    "depends"      : [
        "Cache::LRU"
    ],
    "test-depends" : [ "Test" ],
    "provides"     : {
        "Web::Cache"         : "lib/Web/Cache.pm6",
        "Web::Cache::Memory" : "lib/Web/Cache/Memory.pm6"
    },
    "authors"      : [ "Sam Morrison" ],
    "source-url"   : "git://github.com/scmorrison/perl6-Web-Cache.git"
}
