{
  "authors" : [
    "Elizabeth Mattijsen"
  ],
  "build-depends" : [ ],
  "depends" : [
    "P5caller",
    "P5chomp",
    "P5chop",
    "P5chr",
    "P5each",
    "P5fc",
    "P5hex",
    "P5index",
    "P5lc",
    "P5lcfirst",
    "P5length",
    "P5oct",
    "P5ord",
    "P5pack",
    "P5quotemeta",
    "P5ref",
    "P5rindex",
    "P5substr",
    "P5tie",
    "P5times",
    "P5uc",
    "P5ucfirst"
  ],
  "description" : "Implement Perl 5's built-in functions",
  "license" : "Artistic-2.0",
  "name" : "P5built-ins",
  "perl" : "6.c",
  "provides" : {
    "P5built-ins" : "lib/P5built-ins.pm6"
  },
  "resources" : [ ],
  "source-url" : "https://github.com/lizmat/P5built-ins.git",
  "tags" : [
    "PERL5",
    "CPAN5"
  ],
  "test-depends" : [ ],
  "version" : "0.0.2"
}
